MANIFEST.in
distribute_setup.py
setup.py
MondayMornings/__init__.py
MondayMornings.egg-info/PKG-INFO
MondayMornings.egg-info/SOURCES.txt
MondayMornings.egg-info/dependency_links.txt
MondayMornings.egg-info/not-zip-safe
MondayMornings.egg-info/requires.txt
MondayMornings.egg-info/top_level.txt
tests/MondayMornings_tests.py
tests/__init__.py