Metadata-Version: 1.0
Name: MondayMornings
Version: 0.1.0
Summary: A project that combines an alarm and weather updates for those annoying monday mornings.
Home-page: https://github.com/ramstush/MondayMornings
Author: Ryan Stush
Author-email: ramstush@gmail.com
License: GPL
Keywords: alarm Monday Mornings MondayMornings
Platform: UNKNOWN
